etllog/__init__.py
etllog/core.py
etllog-0.1.1.dist-info/LICENSE.md
etllog-0.1.1.dist-info/METADATA
etllog-0.1.1.dist-info/WHEEL
etllog-0.1.1.dist-info/top_level.txt
etllog-0.1.1.dist-info/RECORD
