Metadata-Version: 2.1
Name: etllog
Version: 0.1.1
Summary: Universal logger with custom levels for ETL and automation processes.
Author: Pedro Dellazzari
Classifier: Programming Language :: Python :: 3
Classifier: Operating System :: OS Independent
Requires-Python: >=3.7
License-File: LICENSE.md
Requires-Dist: colorlog>=6.7.0
